TreeOrdination/TreeOrdination.py
TreeOrdination/__init__.py
TreeOrdination/feature_importance_treeord.py
TreeOrdination/transformers_treeord.py
treeordination-1.3.5.dist-info/METADATA
treeordination-1.3.5.dist-info/WHEEL
treeordination-1.3.5.dist-info/licenses/LICENSE
treeordination-1.3.5.dist-info/RECORD
