Metadata-Version: 2.4
Name: TreeOrdination
Version: 1.3.5
Summary: Projection of High-Dimensional Data Using Multivariate Decision Trees and UMAP
Project-URL: Homepage, https://github.com/jrudar/TreeOrdination
Project-URL: Repository, https://github.com/jrudar/TreeOrdination.git
Project-URL: Bug Tracker, https://github.com/jrudar/TreeOrdination/issues
Author: G. Brian Golding, Stefan C. Kremer
Author-email: Josip Rudar <joe.rudar@inspection.gc.ca>, Mehrdad Hajibabaei <mhajibab@uoguelph.ca>
License: MIT License
License-File: LICENSE
Keywords: dimensionality reduction,ecology,multivariate statistics
Classifier: Development Status :: 5 - Production/Stable
Classifier: Intended Audience :: Science/Research
Classifier: License :: OSI Approved :: MIT License
Classifier: Natural Language :: English
Classifier: Operating System :: OS Independent
Classifier: Programming Language :: Python :: 3
Classifier: Programming Language :: Python :: 3 :: Only
Classifier: Programming Language :: Python :: 3.11
Classifier: Programming Language :: Python :: 3.12
Classifier: Programming Language :: Python :: 3.13
Requires-Python: >=3.11
Requires-Dist: landmarkclassifier>=2.1.0
Requires-Dist: numpy==2.1.3
Requires-Dist: scikit-learn>=1.6.1
Requires-Dist: seaborn
Requires-Dist: shap>=0.47.1
Requires-Dist: umap-learn>=0.5.7
Provides-Extra: dev
Requires-Dist: black; extra == 'dev'
Requires-Dist: mypy; extra == 'dev'
Requires-Dist: ruff; extra == 'dev'
Requires-Dist: twine; extra == 'dev'
Provides-Extra: test
Requires-Dist: pytest; extra == 'test'
Requires-Dist: pytest-cov; extra == 'test'
